unbound_key_control_client_api/__init__.py
unbound_key_control_client_api/models/__init__.py
unbound_key_control_client_api/models/clients.py
unbound_key_control_client_api/models/keys.py
unbound_key_control_client_api/models/partitions.py
unbound_key_control_client_api/models/roles.py
unbound_key_control_client_api/models/users.py
unbound_key_control_client_api/ukc_client.py
unbound_key_control_client_api/views/__init__.py
unbound_key_control_client_api/views/clients.py
unbound_key_control_client_api/views/roles.py
unbound_key_control_client_api-0.16.1.dist-info/LICENSE.md
unbound_key_control_client_api-0.16.1.dist-info/WHEEL
unbound_key_control_client_api-0.16.1.dist-info/METADATA
unbound_key_control_client_api-0.16.1.dist-info/RECORD
