Metadata-Version: 2.1
Name: unbound-key-control-client-api
Version: 0.16.1
Summary: Client API for Unbound Key Control
Author: Jerod Gawne
Author-email: jerodgawne@gmail.com
Requires-Python: >=3.9.0,<4.0.0
Classifier: Programming Language :: Python :: 3
Classifier: Programming Language :: Python :: 3.9
Requires-Dist: base-client-api (>=2.4.1,<3.0.0)
